{
 "chart_name": "Daily Purchase Value",
 "chart_type": "Sum",
 "custom_options": "{\"type\": \"line\"}",
 "docstatus": 0,
 "doctype": "Dashboard Chart",
 "dynamic_filters_json": "{}",
 "filters_json": "[[\"Purchases\",\"docstatus\",\"!=\",\"2\"],[\"Purchases\",\"purchase_date\",\"Timespan\",\"last 30 days\"]]",
 "idx": 0,
 "is_public": 0,
 "is_standard": 1,
 "module": "Supply Chain",
 "name": "Daily Purchase Value",
 "number_of_groups": 0,
 "timespan": "Last 30 days",
 "time_interval": "Daily",
 "timeseries": 1,
 "type": "Line",
 "use_report_chart": 0,
 "y_axis": [
  {
   "aggregate_function_based_on": "total_price",
   "color": "#6366f1",
   "label": "ETB"
  }
 ],
 "based_on": "purchase_date",
 "document_type": "Purchases"
}
